django_pipstatus-0.1.3.dist-info/DESCRIPTION.rst
django_pipstatus-0.1.3.dist-info/METADATA
django_pipstatus-0.1.3.dist-info/RECORD
django_pipstatus-0.1.3.dist-info/WHEEL
django_pipstatus-0.1.3.dist-info/metadata.json
django_pipstatus-0.1.3.dist-info/top_level.txt
pipstatus/__init__.py
pipstatus/models.py
pipstatus/urls.py
pipstatus/views.py
pipstatus/migrations/__init__.py
pipstatus/templates/pipstatus.html
pipstatus/templates/pipstatus_bootstrap3.html
pipstatus/templates/pipstatus_standalone.html
pipstatus/templatetags/__init__.py
pipstatus/templatetags/pipstatus.py
