Metadata-Version: 2.0
Name: django-pipstatus
Version: 0.1.3
Summary: Django pipstatus
Home-page: https://github.com/soerenbe/django-pipstatus
Author: Sören Berger
Author-email: soeren.berger@u1337.de
License: GPL-v2
Keywords: django pip
Platform: UNKNOWN
Classifier: Development Status :: 3 - Alpha
Classifier: Intended Audience :: Developers
Classifier: Framework :: Django
Classifier: License :: OSI Approved :: GNU General Public License v2 (GPLv2)
Classifier: Programming Language :: Python :: 2.7
Classifier: Programming Language :: Python :: 3
Requires-Dist: django
Requires-Dist: pip (>=7)
